<?xml version = '1.0' encoding = 'UTF-8'?>
<Relation class="oracle.dbtools.crest.model.design.logical.Relation" name="ZAMOWIENIA_Materiały_FK" directorySegmentName="seg_0" id="24086B01-C08D-CEDE-8B4D-AB643F71A653">
<createdBy>rafal</createdBy>
<createdTime>2024-12-16 09:13:34 UTC</createdTime>
<generatorID>52703A40-52B7-FD1A-EAE9-5F7EBDB89F11</generatorID>
<ownerDesignName>diagram_relacji_proj_v2</ownerDesignName>
<engineerTo>
<item key="EEE16998-D2EC-EC94-FEC3-9E5F67C7DF87" value="true"/>
</engineerTo>
<sourcePk>BAA1DA9A-F884-671D-2D4F-3C55B60F1FB7</sourcePk>
<identifying>false</identifying>
<optionalSource>true</optionalSource>
<optionalTarget>false</optionalTarget>
<sourceCardinality>1</sourceCardinality>
<sourceEntity>9C11056F-7A01-27BE-9B6A-38801E4940B7</sourceEntity>
<targetCardinalityString>*</targetCardinalityString>
<targetEntity>010AFA03-BAE2-6B5C-F794-2881C7F8577A</targetEntity>
<transferable>true</transferable>
<deleteRule>NO ACTION</deleteRule>
</Relation>